ehelply_python_experimental_sdk/__init__.py
ehelply_python_experimental_sdk/api_client.py
ehelply_python_experimental_sdk/configuration.py
ehelply_python_experimental_sdk/exceptions.py
ehelply_python_experimental_sdk/rest.py
ehelply_python_experimental_sdk/schemas.py
ehelply_python_experimental_sdk/api/__init__.py
ehelply_python_experimental_sdk/api/appointments_api.py
ehelply_python_experimental_sdk/api/billing_api.py
ehelply_python_experimental_sdk/api/catalogs_api.py
ehelply_python_experimental_sdk/api/category_api.py
ehelply_python_experimental_sdk/api/companies_api.py
ehelply_python_experimental_sdk/api/content_api.py
ehelply_python_experimental_sdk/api/facts_api.py
ehelply_python_experimental_sdk/api/fields_api.py
ehelply_python_experimental_sdk/api/logging_api.py
ehelply_python_experimental_sdk/api/meta_api.py
ehelply_python_experimental_sdk/api/monitor_api.py
ehelply_python_experimental_sdk/api/notes_api.py
ehelply_python_experimental_sdk/api/places_api.py
ehelply_python_experimental_sdk/api/products_api.py
ehelply_python_experimental_sdk/api/projects_api.py
ehelply_python_experimental_sdk/api/reviews_api.py
ehelply_python_experimental_sdk/api/security_api.py
ehelply_python_experimental_sdk/api/staff_api.py
ehelply_python_experimental_sdk/api/support_api.py
ehelply_python_experimental_sdk/api/tag_api.py
ehelply_python_experimental_sdk/api/tags_api.py
ehelply_python_experimental_sdk/api/users_api.py
ehelply_python_experimental_sdk/api/appointments_api_endpoints/__init__.py
ehelply_python_experimental_sdk/api/appointments_api_endpoints/add_entity_to_appointment.py
ehelply_python_experimental_sdk/api/appointments_api_endpoints/create_appointment.py
ehelply_python_experimental_sdk/api/appointments_api_endpoints/delete_appointment.py
ehelply_python_experimental_sdk/api/appointments_api_endpoints/detach_entity_from_appointment.py
ehelply_python_experimental_sdk/api/appointments_api_endpoints/get_appointment.py
ehelply_python_experimental_sdk-1.1.118.dist-info/METADATA
ehelply_python_experimental_sdk-1.1.118.dist-info/WHEEL
ehelply_python_experimental_sdk-1.1.118.dist-info/top_level.txt
ehelply_python_experimental_sdk-1.1.118.dist-info/RECORD
